PyNutrition/PyNutrition.py
PyNutrition/__init__.py
PyNutrition-0.0.5.dist-info/LICENSE
PyNutrition-0.0.5.dist-info/METADATA
PyNutrition-0.0.5.dist-info/WHEEL
PyNutrition-0.0.5.dist-info/top_level.txt
PyNutrition-0.0.5.dist-info/RECORD
