Metadata-Version: 2.1
Name: PyNutrition
Version: 0.0.5
Summary: A small package
Author: Hudson R Bandeira
Author-email: hudsonrb750@gmail.com
Classifier: Programming Language :: Python :: 3
Classifier: License :: OSI Approved :: MIT License
Classifier: Operating System :: OS Independent
Requires-Python: >=3.8
License-File: LICENSE
